mae/__init__.py
mae/cli.py
mae/mae.py
mae-1.0.11.dist-info/LICENSE
mae-1.0.11.dist-info/METADATA
mae-1.0.11.dist-info/WHEEL
mae-1.0.11.dist-info/entry_points.txt
mae-1.0.11.dist-info/top_level.txt
mae-1.0.11.dist-info/RECORD
