Metadata-Version: 2.1
Name: mae
Version: 1.0.11
Summary: Mesos App Exporter for Prometheus
Home-page: https://github.com/paambaati/mae
Author: GP
Author-email: me@httgp.com
License: MIT
Platform: UNKNOWN
Classifier: License :: OSI Approved :: MIT License
Classifier: Programming Language :: Python
Classifier: Programming Language :: Python :: 2
Classifier: Programming Language :: Python :: 2.7
Classifier: Programming Language :: Python :: 3
Classifier: Programming Language :: Python :: 3.6
Requires-Python: >=2.7.0
Requires-Dist: requests
Requires-Dist: six
Requires-Dist: mock
